MANIFEST.in
README.md
pyproject.toml
setup.py
src/stdiomask/__init__.py
src/stdiomask.egg-info/PKG-INFO
src/stdiomask.egg-info/SOURCES.txt
src/stdiomask.egg-info/dependency_links.txt
src/stdiomask.egg-info/top_level.txt