Metadata-Version: 2.1
Name: stdiomask
Version: 0.0.6
Summary: A cross-platform Python module for entering passwords to a stdio terminal and displaying a **** mask, which getpass cannot do.
Home-page: https://github.com/asweigart/stdiomask
Author: Al Sweigart
Author-email: al@inventwithpython.com
License: GPLv3+
Platform: UNKNOWN
Classifier: License :: OSI Approved :: GNU General Public License v3 or later (GPLv3+)
Classifier: Programming Language :: Python
Classifier: Programming Language :: Python :: 2
Classifier: Programming Language :: Python :: 2.7
Classifier: Programming Language :: Python :: 3
Classifier: Programming Language :: Python :: 3.4
Classifier: Programming Language :: Python :: 3.5
Classifier: Programming Language :: Python :: 3.6
Classifier: Programming Language :: Python :: 3.7
Classifier: Programming Language :: Python :: 3.8
Classifier: Programming Language :: Python :: 3.9
